week9/Example.v
module Example(output reg [3:0] A_par,input [3:0] I_par, input s1,s0, MSB_in,LSB_in,CLK,Clear_b);

always @(posedge CLK, negedge Clear_b)
if(Clear_b==0)A_par<=4'b0000;
else
case({s1,s0})
2'b00:A_par<=A_par;
2'b01:A_par<={MSB_in,A_par[3:1]};
2'b10:A_par<={A_par[2:0],LSB_in};
2'b11:A_par<=I_par;
endcase
endmodule

week9/t_Example.v
`timescale 1ns/10ps

module t_Example;
wire [3:0] A_par;
reg [3:0] I_par;
reg s1,s0,MSB_in,LSB_in,CLK,Clear_b;
Example E1(A_par,I_par,s1,s0,MSB_in,LSB_in,CLK,Clear_b);




initial
begin
$dumpfile("Example.vcd");
$dumpvars(0,t_Example);
s1=1'b1;
s0=1'b1;
end

initial
begin
s1=1'b1;
repeat(7)
#100 s1=~s1;
end

initial
begin
s0=1'b1;
repeat(14)
#50 s0=~s0;
end

initial
begin
CLK=1'b0;
repeat(100)
#10 CLK=~CLK;
end

initial
begin
Clear_b=1'b1;
repeat(4)
#100 Clear_b=~Clear_b;
end

initial
begin
MSB_in=1'b1;
LSB_in=1'b0;
end

initial
begin 
I_par=4'b0000;
repeat(12)
#50 I_par=I_par+1;
end
/*initial 
begin
I_par=4'b0000;
#30; I_par=4'b0001;
#60; I_par=4'b0010;
#90; I_par=4'b0011;
#120; I_par=4'b0100;
#150; I_par=4'b0101;
#180; I_par=4'b0110;
#210; I_par=4'b0111;
#240; I_par=4'b1000;
#270; I_par=4'b1001;
#300; I_par=4'b1010;
#330; I_par=4'b1011;
#360; I_par=4'b1100;
#390; I_par=4'b1101;
#420; I_par=4'b1110;
#450; I_par=4'b1111;
end*/

initial #800 $finish;

endmodule

week9/Example.vcd
$date
	Fri Nov 11 17:06:38 2016
$end
$version
	Icarus Verilog
$end
$timescale
	10ps
$end
$scope module t_Example $end
$var wire 4 ! A_par [3:0] $end
$var reg 1 " CLK $end
$var reg 1 # Clear_b $end
$var reg 4 $ I_par [3:0] $end
$var reg 1 % LSB_in $end
$var reg 1 & MSB_in $end
$var reg 1 ' s0 $end
$var reg 1 ( s1 $end
$scope module E1 $end
$var wire 1 ) CLK $end
$var wire 1 * Clear_b $end
$var wire 4 + I_par [3:0] $end
$var wire 1 , LSB_in $end
$var wire 1 - MSB_in $end
$var wire 1 . s0 $end
$var wire 1 / s1 $end
$var reg 4 0 A_par [3:0] $end
$upscope $end
$upscope $end
$enddefinitions $end
#0
$dumpvars
bx 0
1/
1.
1-
0,
b0 +
1*
0)
1(
1'
1&
0%
b0 $
1#
0"
bx !
$end
#1000
b0 0
b0 !
1"
1)
#2000
0"
0)
#3000
1"
1)
#4000
0"
0)
#5000
1"
1)
b1 $
b1 +
0'
0.
#6000
0"
0)
#7000
1"
1)
#8000
0"
0)
#9000
1"
1)
#10000
0"
0)
b10 $
b10 +
1'
1.
0#
0*
0(
0/
#11000
1"
1)
#12000
0"
0)
#13000
1"
1)
#14000
0"
0)
#15000
1"
1)
b11 $
b11 +
0'
0.
#16000
0"
0)
#17000
1"
1)
#18000
0"
0)
#19000
1"
1)
#20000
0"
0)
b100 $
b100 +
1'
1.
1#
1*
1(
1/
#21000
b100 0
b100 !
1"
1)
#22000
0"
0)
#23000
1"
1)
#24000
0"
0)
#25000
b1000 0
b1000 !
1"
1)
b101 $
b101 +
0'
0.
#26000
0"
0)
#27000
b0 0
b0 !
1"
1)
#28000
0"
0)
#29000
1"
1)
#30000
0"
0)
b110 $
b110 +
1'
1.
0#
0*
0(
0/
#31000
1"
1)
#32000
0"
0)
#33000
1"
1)
#34000
0"
0)
#35000
1"
1)
b111 $
b111 +
0'
0.
#36000
0"
0)
#37000
1"
1)
#38000
0"
0)
#39000
1"
1)
#40000
0"
0)
b1000 $
b1000 +
1'
1.
1#
1*
1(
1/
#41000
b1000 0
b1000 !
1"
1)
#42000
0"
0)
#43000
1"
1)
#44000
0"
0)
#45000
b0 0
b0 !
1"
1)
b1001 $
b1001 +
0'
0.
#46000
0"
0)
#47000
1"
1)
#48000
0"
0)
#49000
1"
1)
#50000
0"
0)
b1010 $
b1010 +
1'
1.
0(
0/
#51000
b1000 0
b1000 !
1"
1)
#52000
0"
0)
#53000
b1100 0
b1100 !
1"
1)
#54000
0"
0)
#55000
1"
1)
b1011 $
b1011 +
0'
0.
#56000
0"
0)
#57000
1"
1)
#58000
0"
0)
#59000
1"
1)
#60000
0"
0)
b1100 $
b1100 +
1'
1.
1(
1/
#61000
1"
1)
#62000
0"
0)
#63000
1"
1)
#64000
0"
0)
#65000
b1000 0
b1000 !
1"
1)
0'
0.
#66000
0"
0)
#67000
b0 0
b0 !
1"
1)
#68000
0"
0)
#69000
1"
1)
#70000
0"
0)
1'
1.
0(
0/
#71000
b1000 0
b1000 !
1"
1)
#72000
0"
0)
#73000
b1100 0
b1100 !
1"
1)
#74000
0"
0)
#75000
b1110 0
b1110 !
1"
1)
#76000
0"
0)
#77000
b1111 0
b1111 !
1"
1)
